[
	{
		"id": 1,
		"image": "clean.jpg",
		"name": "lowl",
		"description": "Lorem ipsum,dolor sit amet consectetur adipisicing elit.",
		"in_store": true,
		"price": 120,
		"sold": 0,
		"canal": "Hotel",
		"items_number": 3,
		"created_at": "2019-05-09 07:02:08",
		"updated_at": "2019-05-10 08:02:08"
	},
	{
		"id": 2,
		"image": "clean.jpg",
		"name": "tani",
		"description": "Lorem ipsum,dolor sit amet consectetur adipisicing elit.",
		"in_store": true,
		"price": 30,
		"sold": 20,
		"canal": "Cafe",
		"items_number": 3,
		"created_at": "2019-05-09 07:02:08",
		"updated_at": "2019-05-10 07:02:08"
	},
	{
		"id": 3,
		"image": "clean.jpg",
		"name": "Brosse 3",
		"description": "Lorem ipsum,dolor sit amet consectetur adipisicing elit.",
		"in_store": false,
		"price": 100,
		"sold": 30,
		"canal": "Restaurant",
		"items_number": 3,
		"created_at": "2019-05-09 07:02:08",
		"updated_at": "2019-05-09 07:02:08"
	},
	{
		"id": 4,
		"image": "clean.jpg",
		"name": "Brosse 4",
		"description": "Lorem ipsum,dolor sit amet consectetur adipisicing elit.",
		"in_store": false,
		"price": 100,
		"sold": 30,
		"canal": "Supermarche",
		"items_number": 3,
		"created_at": "2019-05-09 07:02:08",
		"updated_at": "2019-05-09 07:02:08"
	},
	{
		"id": 5,
		"image": "clean.jpg",
		"name": "Brosse 5",
		"description": "Lorem ipsum,dolor sit amet consectetur adipisicing elit.",
		"in_store": false,
		"price": 100,
		"sold": 30,
		"canal": "PDV",
		"items_number": 3,
		"created_at": "2019-05-09 07:02:08",
		"updated_at": "2019-05-09 07:02:08"
	},
	{
		"id": 10,
		"image": "clean.jpg",
		"name": "Brosse 10",
		"description": "Lorem ipsum,dolor sit amet consectetur adipisicing elit.",
		"in_store": true,
		"price": 120,
		"sold": 0,
		"canal": "Hotel",
		"items_number": 3,
		"created_at": "2019-05-09 07:02:08",
		"updated_at": "2019-05-09 07:02:08"
	},
	{
		"id": 20,
		"image": "clean.jpg",
		"name": "Brosse 20",
		"description": "Lorem ipsum,dolor sit amet consectetur adipisicing elit.",
		"in_store": true,
		"price": 30,
		"sold": 20,
		"canal": "Cafe",
		"items_number": 3,
		"created_at": "2019-05-09 07:02:08",
		"updated_at": "2019-05-09 07:02:08"
	},
	{
		"id": 30,
		"image": "clean.jpg",
		"name": "Brosse 30",
		"description": "Lorem ipsum,dolor sit amet consectetur adipisicing elit.",
		"in_store": false,
		"price": 100,
		"sold": 30,
		"canal": "Restaurant",
		"items_number": 3,
		"created_at": "2019-05-09 07:02:08",
		"updated_at": "2019-05-09 07:02:08"
	},
	{
		"id": 40,
		"image": "clean.jpg",
		"name": "Brosse 40",
		"description": "Lorem ipsum,dolor sit amet consectetur adipisicing elit.",
		"in_store": false,
		"price": 100,
		"sold": 30,
		"canal": "Supermarche",
		"items_number": 3,
		"created_at": "2019-05-09 07:02:08",
		"updated_at": "2019-05-09 07:02:08"
	},
	{
		"id": 50,
		"image": "clean.jpg",
		"name": "Brosse 50",
		"description": "Lorem ipsum,dolor sit amet consectetur adipisicing elit.",
		"in_store": false,
		"price": 100,
		"sold": 30,
		"canal": "PDV",
		"items_number": 3,
		"created_at": "2019-05-09 07:02:08",
		"updated_at": "2019-05-09 07:02:08"
	},
	{
		"id": 11,
		"image": "clean.jpg",
		"name": "Brosse 11",
		"description": "Lorem ipsum,dolor sit amet consectetur adipisicing elit.",
		"in_store": true,
		"price": 120,
		"sold": 0,
		"canal": "Hotel",
		"items_number": 3,
		"created_at": "2019-05-09 07:02:08",
		"updated_at": "2019-05-09 07:02:08"
	},
	{
		"id": 21,
		"image": "clean.jpg",
		"name": "Brosse 12",
		"description": "Lorem ipsum,dolor sit amet consectetur adipisicing elit.",
		"in_store": true,
		"price": 30,
		"sold": 20,
		"canal": "Cafe",
		"items_number": 3,
		"created_at": "2019-05-09 07:02:08",
		"updated_at": "2019-05-09 07:02:08"
	},
	{
		"id": 31,
		"image": "clean.jpg",
		"name": "Brosse 31",
		"description": "Lorem ipsum,dolor sit amet consectetur adipisicing elit.",
		"in_store": false,
		"price": 100,
		"sold": 30,
		"canal": "Restaurant",
		"items_number": 3,
		"created_at": "2019-05-09 07:02:08",
		"updated_at": "2019-05-09 07:02:08"
	},
	{
		"id": 41,
		"image": "clean.jpg",
		"name": "Brosse 41",
		"description": "Lorem ipsum,dolor sit amet consectetur adipisicing elit.",
		"in_store": false,
		"price": 100,
		"sold": 30,
		"canal": "Supermarche",
		"items_number": 3,
		"created_at": "2019-05-09 07:02:08",
		"updated_at": "2019-05-09 07:02:08"
	},
	{
		"id": 51,
		"image": "clean.jpg",
		"name": "Brosse 51",
		"description": "Lorem ipsum,dolor sit amet consectetur adipisicing elit.",
		"in_store": false,
		"price": 100,
		"sold": 30,
		"canal": "PDV",
		"items_number": 3,
		"created_at": "2019-05-09 07:02:08",
		"updated_at": "2019-05-09 07:02:08"
	},
	{
		"id": 101,
		"image": "clean.jpg",
		"name": "Brosse 101",
		"description": "Lorem ipsum,dolor sit amet consectetur adipisicing elit.",
		"in_store": true,
		"price": 120,
		"sold": 0,
		"canal": "Hotel",
		"items_number": 3,
		"created_at": "2019-05-09 07:02:08",
		"updated_at": "2019-05-09 07:02:08"
	},
	{
		"id": 201,
		"image": "clean.jpg",
		"name": "Brosse 201",
		"description": "Lorem ipsum,dolor sit amet consectetur adipisicing elit.",
		"in_store": true,
		"price": 30,
		"sold": 20,
		"canal": "Cafe",
		"items_number": 3,
		"created_at": "2019-05-09 07:02:08",
		"updated_at": "2019-05-09 07:02:08"
	},
	{
		"id": 301,
		"image": "clean.jpg",
		"name": "Brosse 301",
		"description": "Lorem ipsum,dolor sit amet consectetur adipisicing elit.",
		"in_store": false,
		"price": 100,
		"sold": 30,
		"canal": "Restaurant",
		"items_number": 3,
		"created_at": "2019-05-09 07:02:08",
		"updated_at": "2019-05-09 07:02:08"
	},
	{
		"id": 401,
		"image": "clean.jpg",
		"name": "Brosse 401",
		"description": "Lorem ipsum,dolor sit amet consectetur adipisicing elit.",
		"in_store": false,
		"price": 100,
		"sold": 30,
		"canal": "Supermarche",
		"items_number": 3,
		"created_at": "2019-05-09 07:02:08",
		"updated_at": "2019-05-09 07:02:08"
	},
	{
		"id": 501,
		"image": "clean.jpg",
		"name": "Brosse 501",
		"description": "Lorem ipsum,dolor sit amet consectetur adipisicing elit.",
		"in_store": false,
		"price": 100,
		"sold": 30,
		"canal": "PDV",
		"items_number": 3,
		"created_at": "2019-05-09 07:02:08",
		"updated_at": "2019-05-09 07:02:08"
	}
]
